Workbook

Sheet Cover
B2: CBRE
B3: Capital Markets | Investment Properties | National Investment Team
B5: ACQUISITION PRO FORMA — CONFIDENTIAL
B6: 70 York Street | Toronto, Ontario | Class A Office Tower
B7: 210,000 SF | 17 Storeys | Financial District | $134,600,000 Asking Price | 6.50% Going-In Cap Rate
B9: PROPERTY SUMMARY
B10: Address | D10: 70 York Street, Toronto, ON
B11: Asset Type | D11: Office — Class A
B12: Building Size | D12: 210,000 SF | 17 Storeys
B13: Submarket | D13: Toronto Financial District / PATH-connected
B14: Occupancy at Acquisition | D14: 92.5% (15,750 SF vacant)
B15: Anchor Tenant | D15: CMHC (Federal Government Covenant)
B16: Year Built / Renovated | D16: Comprehensively repositioned 2022–2024
B18: TRANSACTION SUMMARY
B19: Vendor | D19: KingSett Senior Mortgage Fund
B20: Purchaser | D20: Desjardins DGAM (60%) / Pension Fund (40%)
B21: Structure | D21: Off-market process; co-advisors CBRE + TD Cornerstone
B22: Asking Price | D22: $134,600,000
B23: Price Per SF | D23: $639 / SF
B24: Going-In Cap Rate | D24: 6.50%
B25: Land Transfer Tax (est.) | D25: $2,692,000
B26: Total All-In Cost / SF | D26: $663 / SF
B28: PREPARED BY
B29: Analyst | D29: Amanda Dolan, CBRE Capital Markets
B30: Date | D30: March 2026
B31: Classification | D31: STRICTLY PRIVATE & CONFIDENTIAL
B33: This analysis has been prepared by CBRE Capital Markets for informational purposes only. Figures are drawn from RENX, CBRE market reports, and analyst estimates. Tenant names are illustrative proxies. This document does not constitute investment advice.

Sheet Assumptions
B2: MODEL ASSUMPTIONS — 70 YORK STREET
B3: Blue cells = hardcoded inputs | All other cells = formulas | Sources documented in column D
B4: PROPERTY
B5: Asking Price | C5: 134600000 | D5: RENX / CBRE Canada Press Release
B6: Total GFA (SF) | C6: 210000 | D6: RENX Exclusive Report, Nov. 2025
B7: Number of Storeys | C7: 17 | D7: RENX Exclusive Report, Nov. 2025
B8: Land Transfer Tax (est.) | C8: 2692000 | D8: Est. ~2.0% of purchase price
B10: REVENUE
B11: Occupancy at Acquisition (Yr 0) | C11: 0.925 | D11: CBRE / RENX — 92.5% at time of sale
B12: Stabilised Occupancy (Yr 2+) | C12: 0.95 | D12: Conservative; AAA submarket vacancy 7.2%
B13: Avg. Net Rent — In-Place ($/SF/yr) | C13: 31 | D13: CBRE Toronto Class A avg. $28–$34/SF
B14: Annual Rent Growth — Yrs 1–5 | C14: 0.025 | D14: OM assumption; Toronto Class A rent growth
B15: Annual Rent Growth — Yrs 6–10 | C15: 0.02 | D15: Long-run normalised
B16: Other Income ($/SF/yr) | C16: 1.5 | D16: Parking, storage — est. for Class A tower
B17: Other Income Growth Rate | C17: 0.02 | D17: Conservative
B19: OPERATING EXPENSES
B20: Property Tax ($/SF/yr) | C20: 3 | D20: Est. ~$3.00/SF; Toronto commercial mill rate
B21: Insurance ($/SF/yr) | C21: 0.5 | D21: Market rate Class A downtown
B22: Property Mgmt Fee (% of EGI) | C22: 0.04 | D22: Standard institutional rate
B23: Repairs & Maintenance ($/SF/yr) | C23: 1.2 | D23: Class A tower; lower than multifamily
B24: Utilities & Common Area ($/SF/yr) | C24: 1.8 | D24: Net lease; landlord portion only
B25: Admin & Other ($/SF/yr) | C25: 0.6 | D25: Estimated
B26: Expense Growth Rate (annual) | C26: 0.02 | D26: CPI-linked
B27: Capital Reserve ($/SF/yr) | C27: 1 | D27: OM assumption; Class A standard
B29: FINANCING
B30: Loan-to-Value (LTV) | C30: 0.6 | D30: Conservative for office; CMHC not available
B31: Interest Rate (annual) | C31: 0.0575 | D31: Senior secured, 5-yr term, 2025 market
B32: Amortization Period (years) | C32: 25 | D32: Standard commercial
B33: Loan Term (years) | C33: 10 | D33: Matches hold period
B35: EXIT & DISCOUNT RATE
B36: Hold Period (years) | C36: 10 | D36: Standard institutional
B37: Exit Cap Rate | C37: 0.0675 | D37: OM assumption; 25 bps expansion from going-in
B38: Disposition Costs (% of gross exit value) | C38: 0.015 | D38: Brokerage + legal
B39: Discount Rate — Unlevered IRR target | C39: 0.0725 | D39: OM assumption; office risk premium

Sheet Rent Roll
B2: TENANCY SCHEDULE & RENT ROLL
B3: 70 York Street, Toronto | Total GFA: 210,000 SF | Occupancy: 92.5% | Tenant names are illustrative proxies (*)
B5: TENANT | C5: SUITE/FLOOR | D5: SF LEASED | E5: % OF GLA | F5: NET RENT ($/SF) | G5: ANN. BASE RENT ($) | H5: LEASE EXPIRY | I5: WALE (YRS)
B6: CMHC (Federal Gov't Covenant)* | C6: Floors 10–13 | D6: 46200 | E6: 0.22 | F6: 32 | G6: 1478400 | H6: Dec 2033 | I6: 7.8
B7: Desjardins Financial Group* | C7: Floors 14–16 | D7: 37800 | E7: 0.18 | F7: 34 | G7: 1285200 | H7: Jun 2032 | I7: 6.3
B8: Torys LLP (Law)* | C8: Floors 6–8 | D8: 29400 | E8: 0.14 | F8: 33.5 | G8: 984900 | H8: Dec 2031 | I8: 5.8
B9: Infrastructure Ontario* | C9: Floor 9 | D9: 16800 | E9: 0.08 | F9: 31 | G9: 520800 | H9: Mar 2030 | I9: 4.3
B10: Retail (Ground Floor)* | C10: Ground | D10: 7350 | E10: 0.035 | F10: 55 | G10: 404250 | H10: Dec 2029 | I10: 3.8
B11: Other Tenants (6)* | C11: Mixed | D11: 36750 | E11: 0.175 | F11: 30.5 | G11: 1120875 | H11: Various | I11: 5.5
B12: VACANT | C12: Floor 5 (part) | D12: 15750 | E12: 0.075 | F12: — | G12: — | H12: — | I12: —
B13: TOTAL / WEIGHTED AVERAGE | C13: 190050 | D13: 1 | F13: 5794425
B15: LEASE EXPIRY PROFILE
B16: PERIOD | C16: % OF GLA | D16: SF EXPIRING
B17: 2025–2026 | C17: 0.04 | D17: 8400
B18: 2027–2028 | C18: 0.08 | D18: 16800
B19: 2029–2030 | C19: 0.22 | D19: 46200
B20: 2031–2032 | C20: 0.41 | D20: 86100
B21: 2033+ | C21: 0.17 | D21: 35700
B22: Vacant | C22: 0.075 | D22: 15750

Sheet T12 NOI
B2: YEAR 1 STABILISED NOI — 70 YORK STREET
B3: Stabilised Yr 1 basis (vacant suite assumed leased by Month 6) | 210,000 SF | Net lease structure
B5: LINE ITEM | C5: YR 1 STABILISED ($) | D5: $/SF/YR | E5: NOTES
B6: REVENUE
B7: Gross Potential Rent (GPR) | C7: 6510000 | D7: =C7/Assumptions!C6 -> 31 | E7: 195,000 occ. SF × $31.00 avg net rent + retail at $55/SF; stabilised occ. 92.9%
B8: Less: Vacancy & Credit Loss | C8: -220725 | D8: =C8/Assumptions!C6 -> -1.0510714 | E8: ~3.5% of GPR; stabilising from 7.5% at acquisition (vacant suite leased by Mo. 6)
B9: Other Income (parking, storage) | C9: 315000 | D9: =C9/Assumptions!C6 -> 1.5 | E9: $1.50/SF; parking revenue for Class A Financial District tower
B10: EFFECTIVE GROSS INCOME (EGI) | C10: =C7+C8+C9 -> 6604275 | D10: =C10/Assumptions!C6 -> 31.448929
B12: OPERATING EXPENSES
B13: Property Tax | C13: -630000 | D13: =C13/Assumptions!C6 -> -3 | E13: $3.00/SF; Toronto commercial mill rate
B14: Insurance | C14: -105000 | D14: =C14/Assumptions!C6 -> -0.5 | E14: $0.50/SF; market rate Class A downtown
B15: Property Management (4.0% of EGI) | C15: =-Assumptions!C20*C10 -> -19812825 | D15: =C15/Assumptions!C6 -> -94.346786 | E15: % of EGI — formula-driven
B16: Repairs & Maintenance | C16: -252000 | D16: =C16/Assumptions!C6 -> -1.2 | E16: $1.20/SF
B17: Utilities & Common Area | C17: -378000 | D17: =C17/Assumptions!C6 -> -1.8 | E17: $1.80/SF net lease; landlord portion
B18: Admin & Other | C18: -126000 | D18: =C18/Assumptions!C6 -> -0.6 | E18: $0.60/SF
B19: TOTAL OPERATING EXPENSES | C19: =SUM(C13:C18) -> -21303825 | D19: =C19/Assumptions!C6 -> -101.44679
B21: NET OPERATING INCOME (NOI) | C21: =C10+C19 -> -14699550 | D21: =C21/Assumptions!C6 -> -69.997857
B23: Capital Reserve (shown below NOI) | C23: -210000 | D23: =C23/Assumptions!C6 -> -1 | E23: $1.00/SF; OM assumption
B24: NOI AFTER RESERVES | C24: =C21+C23 -> -14909550 | D24: =C24/Assumptions!C6 -> -70.997857
B26: KEY METRICS
B27: Stabilised NOI (Yr 1) | C27: =C21 -> -14699550
B28: NOI Per SF ($/yr) | C28: =C21/Assumptions!C6 -> -69.997857
B29: Going-In Cap Rate (NOI / Asking Price) | C29: =C21/Assumptions!C5 -> -0.10920914
B30: Expense Ratio (Total OpEx / EGI) | C30: =ABS(C19)/C10 -> 3.2257629
B31: NOI Margin (NOI / EGI) | C31: =C21/C10 -> -2.2257629
B32: Direct Cap Value (NOI / 6.50%) | C32: =C21/0.065 -> -2.2614692e+08
B33: Note: Price vs. Direct Cap Premium | C33: =Assumptions!C5-(C21/0.065) -> 3.6074692e+08

Sheet 10-Yr DCF
B2: 10-YEAR DISCOUNTED CASH FLOW MODEL — 70 YORK STREET
B3: 70 York Street, Toronto Financial District | 210,000 SF Class A Office | 10-Year Hold
B5: LINE ITEM | C5: Year 1 | D5: Year 2 | E5: Year 3 | F5: Year 4 | G5: Year 5 | H5: Year 6 | I5: Year 7 | J5: Year 8 | K5: Year 9 | L5: Year 10 | M5: EXIT
B6: Calendar Year | C6: 2026 | D6: 2027 | E6: 2028 | F6: 2029 | G6: 2030 | H6: 2031 | I6: 2032 | J6: 2033 | K6: 2034 | L6: 2035
B8: REVENUE
B9: Gross Potential Rent | C9: =Assumptions!C6*Assumptions!C12*Assumptions!C13 -> 6184500 | D9: =C9*(1+Assumptions!C14) -> 6339112.5 | E9: =D9*(1+Assumptions!C14) -> 6497590.3 | F9: =E9*(1+Assumptions!C14) -> 6660030.1 | G9: =F9*(1+Assumptions!C14) -> 6826530.8 | H9: =G9*(1+Assumptions!C15) -> 6963061.4 | I9: =H9*(1+Assumptions!C15) -> 7102322.7 | J9: =I9*(1+Assumptions!C15) -> 7244369.1 | K9: =J9*(1+Assumptions!C15) -> 7389256.5 | L9: =K9*(1+Assumptions!C15) -> 7537041.6
B10: Less: Vacancy & Credit Loss | C10: =-(1-Assumptions!C12)*C9 -> -309225 | D10: =-(1-Assumptions!C12)*D9 -> -316955.62 | E10: =-(1-Assumptions!C12)*E9 -> -324879.52 | F10: =-(1-Assumptions!C12)*F9 -> -333001.5 | G10: =-(1-Assumptions!C12)*G9 -> -341326.54 | H10: =-(1-Assumptions!C12)*H9 -> -348153.07 | I10: =-(1-Assumptions!C12)*I9 -> -355116.13 | J10: =-(1-Assumptions!C12)*J9 -> -362218.46 | K10: =-(1-Assumptions!C12)*K9 -> -369462.83 | L10: =-(1-Assumptions!C12)*L9 -> -376852.08
B11: Other Income | C11: =Assumptions!C16*Assumptions!C6 -> 315000 | D11: =C11*(1+Assumptions!C17) -> 321300 | E11: =D11*(1+Assumptions!C17) -> 327726 | F11: =E11*(1+Assumptions!C17) -> 334280.52 | G11: =F11*(1+Assumptions!C17) -> 340966.13 | H11: =G11*(1+Assumptions!C17) -> 347785.45 | I11: =H11*(1+Assumptions!C17) -> 354741.16 | J11: =I11*(1+Assumptions!C17) -> 361835.99 | K11: =J11*(1+Assumptions!C17) -> 369072.71 | L11: =K11*(1+Assumptions!C17) -> 376454.16
B12: EFFECTIVE GROSS INCOME (EGI) | C12: =C9+C10+C11 -> 6190275 | D12: =D9+D10+D11 -> 6343456.9 | E12: =E9+E10+E11 -> 6500436.8 | F12: =F9+F10+F11 -> 6661309.1 | G12: =G9+G10+G11 -> 6826170.4 | H12: =H9+H10+H11 -> 6962693.8 | I12: =I9+I10+I11 -> 7101947.7 | J12: =J9+J10+J11 -> 7243986.6 | ... L12: =L9+L10+L11 -> 7536643.7
B14: OPERATING EXPENSES
B15: Property Tax | C15: =-Assumptions!C20*Assumptions!C6 -> -630000 | D15: =C15*(1+Assumptions!C26) -> -642600 | E15: =D15*(1+Assumptions!C26) -> -655452 | F15: =E15*(1+Assumptions!C26) -> -668561.04 | G15: =F15*(1+Assumptions!C26) -> -681932.26 | H15: =G15*(1+Assumptions!C26) -> -695570.91 | I15: =H15*(1+Assumptions!C26) -> -709482.32 | J15: =I15*(1+Assumptions!C26) -> -723671.97 | K15: =J15*(1+Assumptions!C26) -> -738145.41 | L15: =K15*(1+Assumptions!C26) -> -752908.32
B16: Insurance | C16: =-Assumptions!C21*Assumptions!C6 -> -105000 | D16: =C16*(1+Assumptions!C26) -> -107100 | E16: =D16*(1+Assumptions!C26) -> -109242 | F16: =E16*(1+Assumptions!C26) -> -111426.84 | G16: =F16*(1+Assumptions!C26) -> -113655.38 | H16: =G16*(1+Assumptions!C26) -> -115928.48 | I16: =H16*(1+Assumptions!C26) -> -118247.05 | J16: =I16*(1+Assumptions!C26) -> -120612 | K16: =J16*(1+Assumptions!C26) -> -123024.24 | L16: =K16*(1+Assumptions!C26) -> -125484.72
B17: Property Management (4.0% EGI) | C17: =-Assumptions!C22*C12 -> -247611 | D17: =-Assumptions!C22*D12 -> -253738.27 | E17: =-Assumptions!C22*E12 -> -260017.47 | F17: =-Assumptions!C22*F12 -> -266452.36 | G17: =-Assumptions!C22*G12 -> -273046.82 | H17: =-Assumptions!C22*H12 -> -278507.75 | I17: =-Assumptions!C22*I12 -> -284077.91 | J17: =-Assumptions!C22*J12 -> -289759.47 | K17: =-Assumptions!C22*K12 -> -295554.66 | L17: =-Assumptions!C22*L12 -> -301465.75
B18: Repairs & Maintenance | C18: =-Assumptions!C23*Assumptions!C6 -> -252000 | D18: =C18*(1+Assumptions!C26) -> -257040 | E18: =D18*(1+Assumptions!C26) -> -262180.8 | F18: =E18*(1+Assumptions!C26) -> -267424.42 | G18: =F18*(1+Assumptions!C26) -> -272772.9 | H18: =G18*(1+Assumptions!C26) -> -278228.36 | I18: =H18*(1+Assumptions!C26) -> -283792.93 | J18: =I18*(1+Assumptions!C26) -> -289468.79 | K18: =J18*(1+Assumptions!C26) -> -295258.16 | L18: =K18*(1+Assumptions!C26) -> -301163.33
B19: Utilities & Common Area | C19: =-Assumptions!C24*Assumptions!C6 -> -378000 | D19: =C19*(1+Assumptions!C26) -> -385560 | E19: =D19*(1+Assumptions!C26) -> -393271.2 | F19: =E19*(1+Assumptions!C26) -> -401136.62 | G19: =F19*(1+Assumptions!C26) -> -409159.36 | H19: =G19*(1+Assumptions!C26) -> -417342.54 | I19: =H19*(1+Assumptions!C26) -> -425689.39 | J19: =I19*(1+Assumptions!C26) -> -434203.18 | K19: =J19*(1+Assumptions!C26) -> -442887.25 | L19: =K19*(1+Assumptions!C26) -> -451744.99
B20: Admin & Other | C20: =-Assumptions!C25*Assumptions!C6 -> -126000 | D20: =C20*(1+Assumptions!C26) -> -128520 | E20: =D20*(1+Assumptions!C26) -> -131090.4 | F20: =E20*(1+Assumptions!C26) -> -133712.21 | G20: =F20*(1+Assumptions!C26) -> -136386.45 | H20: =G20*(1+Assumptions!C26) -> -139114.18 | I20: =H20*(1+Assumptions!C26) -> -141896.46 | J20: =I20*(1+Assumptions!C26) -> -144734.39 | K20: =J20*(1+Assumptions!C26) -> -147629.08 | L20: =K20*(1+Assumptions!C26) -> -150581.66
B21: Capital Reserves | C21: =-Assumptions!C27*Assumptions!C6 -> -210000 | D21: =C21*(1+Assumptions!C26) -> -214200 | E21: =D21*(1+Assumptions!C26) -> -218484 | F21: =E21*(1+Assumptions!C26) -> -222853.68 | G21: =F21*(1+Assumptions!C26) -> -227310.75 | H21: =G21*(1+Assumptions!C26) -> -231856.97 | I21: =H21*(1+Assumptions!C26) -> -236494.11 | J21: =I21*(1+Assumptions!C26) -> -241223.99 | K21: =J21*(1+Assumptions!C26) -> -246048.47 | L21: =K21*(1+Assumptions!C26) -> -250969.44
B22: TOTAL OPERATING EXPENSES | C22: =SUM(C15:C21) -> -1948611 | D22: =SUM(D15:D21) -> -1988758.3 | E22: =SUM(E15:E21) -> -2029737.9 | F22: =SUM(F15:F21) -> -2071567.2 | G22: =SUM(G15:G21) -> -2114263.9 | H22: =SUM(H15:H21) -> -2156549.2 | I22: =SUM(I15:I21) -> -2199680.2 | J22: =SUM(J15:J21) -> -2243673.8 | ... L22: =SUM(L15:L21) -> -2334318.2
B24: NET OPERATING INCOME (NOI) | C24: =C12+C22 -> 4241664 | D24: =D12+D22 -> 4354698.6 | E24: =E12+E22 -> 4470698.9 | F24: =F12+F22 -> 4589741.9 | G24: =G12+G22 -> 4711906.5 | H24: =H12+H22 -> 4806144.6 | I24: =I12+I22 -> 4902267.5 | J24: =J12+J22 -> 5000312.9 | ... L24: =L12+L22 -> 5202325.5
B26: DEBT SERVICE (LEVERED)
B27: Loan Amount (at acquisition) | C27: =Assumptions!C5*Assumptions!C30 -> 80760000
B28: Annual Debt Service (PMT) | C28: =PMT(Assumptions!C31/12,Assumptions!C32*12,-C27)*12 -> 6096796 | D28: =PMT(Assumptions!C31/12,Assumptions!C32*12,-C27)*12 -> 6096796 | E28: =PMT(Assumptions!C31/12,Assumptions!C32*12,-C27)*12 -> 6096796 | F28: =PMT(Assumptions!C31/12,Assumptions!C32*12,-C27)*12 -> 6096796 | G28: =PMT(Assumptions!C31/12,Assumptions!C32*12,-C27)*12 -> 6096796 | H28: =PMT(Assumptions!C31/12,Assumptions!C32*12,-C27)*12 -> 6096796 | I28: =PMT(Assumptions!C31/12,Assumptions!C32*12,-C27)*12 -> 6096796 | J28: =PMT(Assumptions!C31/12,Assumptions!C32*12,-C27)*12 -> 6096796 | K28: =PMT(Assumptions!C31/12,Assumptions!C32*12,-C27)*12 -> 6096796 | L28: =PMT(Assumptions!C31/12,Assumptions!C32*12,-C27)*12 -> 6096796
B29: LEVERED CASH FLOW | C29: =C24+C28 -> 10338460 | D29: =D24+D28 -> 10451495 | E29: =E24+E28 -> 10567495 | F29: =F24+F28 -> 10686538 | G29: =G24+G28 -> 10808702 | H29: =H24+H28 -> 10902941 | I29: =I24+I28 -> 10999063 | J29: =J24+J28 -> 11097109 | ... L29: =L24+L28 -> 11299121
B31: EXIT VALUATION — YEAR 10
B32: Exit NOI (Year 11 = Yr 10 × LT growth) | M32: =L24*(1+Assumptions!C15) -> 5306372
B33: Gross Exit Value (Exit NOI ÷ Exit Cap) | M33: =M32/Assumptions!C37 -> 78612919
B34: Less: Disposition Costs (1.50%) | M34: =-Assumptions!C38*M33 -> -1179193.8
B35: Less: Remaining Loan Balance | M35: =-PV(Assumptions!C31/12,(Assumptions!C32-Assumptions!C33)*12,PMT(Assumptions!C31/12,Assumptions!C32*12,-C27)) -> 61182582
B36: NET SALE PROCEEDS (LEVERED) | M36: =M33+M34+M35 -> 1.3861631e+08
B38: RETURNS SUMMARY
B39: Equity Invested | C39: =Assumptions!C5-C27 -> 53840000
B40: Unlevered IRR | C40: =IRR(C55:M55) -> -0.0089509079
B41: Levered IRR | C41: =IRR(C56:M56) -> 0.24614706
B42: Equity Multiple (Levered) | C42: =(SUM(C29:L29)+M36+C39)/C39 -> 5.5870049
B43: Going-In Cap Rate (Yr 1 NOI / Price) | C43: =C24/Assumptions!C5 -> 0.031513105
B44: Exit Cap Rate | C44: =Assumptions!C33 -> 10
C55: =-Assumptions!C5 -> -134600000 | D55: =C24 -> 4241664 | E55: =D24 -> 4354698.6 | F55: =E24 -> 4470698.9 | G55: =F24 -> 4589741.9 | H55: =G24 -> 4711906.5 | I55: =H24 -> 4806144.6 | J55: =I24 -> 4902267.5 | K55: =J24 -> 5000312.9 | L55: =K24 -> 5100319.1 | M55: =L24+M33+M34 -> 82636050
C56: =-C39 -> -53840000 | D56: =C29 -> 10338460 | E56: =D29 -> 10451495 | F56: =E29 -> 10567495 | G56: =F29 -> 10686538 | H56: =G29 -> 10808702 | I56: =H29 -> 10902941 | J56: =I29 -> 10999063 | K56: =J29 -> 11097109 | L56: =K29 -> 11197115 | M56: =L29+M36 -> 1.4991543e+08

Sheet Direct Cap
B2: DIRECT CAPITALIZATION VALUATION — 70 YORK STREET
B3: Value = NOI ÷ Cap Rate | Yr 1 Stabilised vs. Yr 3 (fully stabilised)
C5: YR 1 STABILISED | D5: YR 3 (FULLY STAB.)
B6: REVENUE
B7: Gross Potential Rent | C7: ='10-Yr DCF'!C9 -> 6184500 | D7: ='10-Yr DCF'!E9 -> 6497590.3
B8: Less: Vacancy | C8: ='10-Yr DCF'!C10 -> -309225 | D8: ='10-Yr DCF'!E10 -> -324879.52
B9: Other Income | C9: ='10-Yr DCF'!C11 -> 315000 | D9: ='10-Yr DCF'!E11 -> 327726
B10: EFFECTIVE GROSS INCOME (EGI) | C10: ='10-Yr DCF'!C12 -> 6190275 | D10: ='10-Yr DCF'!E12 -> 6500436.8
B12: OPERATING EXPENSES
B13: Total Operating Expenses | C13: ='10-Yr DCF'!C22 -> -1948611 | D13: ='10-Yr DCF'!E22 -> -2029737.9
B15: NET OPERATING INCOME (NOI) | C15: ='10-Yr DCF'!C24 -> 4241664 | D15: ='10-Yr DCF'!E24 -> 4470698.9
B17: CAPITALISATION
B18: Applied Cap Rate | C18: =Assumptions!C33+0.0025 -> 10.0025 | D18: =Assumptions!C33 -> 10
B20: INDICATED VALUE (NOI ÷ Cap Rate) | C20: ='10-Yr DCF'!C24/C18 -> 424060.38 | D20: ='10-Yr DCF'!E24/D18 -> 447069.89
B21: Value Per SF | C21: =C20/Assumptions!C6 -> 2.0193352 | D21: =D20/Assumptions!C6 -> 2.1289043
B23: ACQUISITION METRICS
B24: Asking Price | C24: =Assumptions!C5 -> 134600000 | D24: =Assumptions!C5 -> 134600000
B25: Asking Price / SF | C25: =Assumptions!C5-C20 -> 1.3417594e+08 | D25: =Assumptions!C5-D20 -> 1.3415293e+08
B26: Premium / (Discount) to Indicated Value

Sheet Sensitivity
B2: SENSITIVITY ANALYSIS — 70 YORK STREET
B3: Three scenario matrices — base case highlighted in green
B5: TABLE 1: INDICATED VALUE ($M) — NOI SCENARIO vs. CAP RATE
B6: NOI \ Cap Rate → | C6: 5.00% | D6: 5.50% | E6: 6.00% | F6: 6.50% | G6: 7.00% | H6: 7.50% | I6: 8.00%
B7: 90% of Base NOI | C7: =('10-Yr DCF'!C24*0.9)/0.05/1000000 -> 76.349952 | D7: =('10-Yr DCF'!C24*0.9)/0.055/1000000 -> 69.409047 | E7: =('10-Yr DCF'!C24*0.9)/0.06/1000000 -> 63.62496 | F7: =('10-Yr DCF'!C24*0.9)/0.065/1000000 -> 58.730732 | G7: =('10-Yr DCF'!C24*0.9)/0.07/1000000 -> 54.53568 | H7: =('10-Yr DCF'!C24*0.9)/0.075/1000000 -> 50.899968 | I7: =('10-Yr DCF'!C24*0.9)/0.08/1000000 -> 47.71872
B8: 95% of Base NOI | C8: =('10-Yr DCF'!C24*0.95)/0.05/1000000 -> 80.591616 | D8: =('10-Yr DCF'!C24*0.95)/0.055/1000000 -> 73.265105 | E8: =('10-Yr DCF'!C24*0.95)/0.06/1000000 -> 67.15968 | F8: =('10-Yr DCF'!C24*0.95)/0.065/1000000 -> 61.993551 | G8: =('10-Yr DCF'!C24*0.95)/0.07/1000000 -> 57.56544 | H8: =('10-Yr DCF'!C24*0.95)/0.075/1000000 -> 53.727744 | I8: =('10-Yr DCF'!C24*0.95)/0.08/1000000 -> 50.36976
B9: 100% of Base NOI | C9: =('10-Yr DCF'!C24*1)/0.05/1000000 -> 84.83328 | D9: =('10-Yr DCF'!C24*1)/0.055/1000000 -> 77.121164 | E9: =('10-Yr DCF'!C24*1)/0.06/1000000 -> 70.6944 | F9: =('10-Yr DCF'!C24*1)/0.065/1000000 -> 65.256369 | G9: =('10-Yr DCF'!C24*1)/0.07/1000000 -> 60.5952 | H9: =('10-Yr DCF'!C24*1)/0.075/1000000 -> 56.55552 | I9: =('10-Yr DCF'!C24*1)/0.08/1000000 -> 53.0208
B10: 105% of Base NOI | C10: =('10-Yr DCF'!C24*1.05)/0.05/1000000 -> 89.074944 | D10: =('10-Yr DCF'!C24*1.05)/0.055/1000000 -> 80.977222 | E10: =('10-Yr DCF'!C24*1.05)/0.06/1000000 -> 74.22912 | F10: =('10-Yr DCF'!C24*1.05)/0.065/1000000 -> 68.519188 | G10: =('10-Yr DCF'!C24*1.05)/0.07/1000000 -> 63.62496 | H10: =('10-Yr DCF'!C24*1.05)/0.075/1000000 -> 59.383296 | I10: =('10-Yr DCF'!C24*1.05)/0.08/1000000 -> 55.67184
B11: 110% of Base NOI | C11: =('10-Yr DCF'!C24*1.1)/0.05/1000000 -> 93.316608 | D11: =('10-Yr DCF'!C24*1.1)/0.055/1000000 -> 84.83328 | E11: =('10-Yr DCF'!C24*1.1)/0.06/1000000 -> 77.76384 | F11: =('10-Yr DCF'!C24*1.1)/0.065/1000000 -> 71.782006 | G11: =('10-Yr DCF'!C24*1.1)/0.07/1000000 -> 66.65472 | H11: =('10-Yr DCF'!C24*1.1)/0.075/1000000 -> 62.211072 | I11: =('10-Yr DCF'!C24*1.1)/0.08/1000000 -> 58.32288
B14: TABLE 2: GOING-IN CAP RATE — NOI SCENARIO vs. PURCHASE PRICE
B15: NOI \ Price → | C15: $110M | D15: $120M | E15: $135M | F15: $145M | G15: $155M | H15: $165M | I15: $180M
B16: 90% of Base NOI | C16: =('10-Yr DCF'!C24*0.9)/110000000 -> 0.034704524 | D16: =('10-Yr DCF'!C24*0.9)/120000000 -> 0.03181248 | E16: =('10-Yr DCF'!C24*0.9)/134600000 -> 0.028361795 | F16: =('10-Yr DCF'!C24*0.9)/145000000 -> 0.02632757 | G16: =('10-Yr DCF'!C24*0.9)/155000000 -> 0.024629017 | H16: =('10-Yr DCF'!C24*0.9)/165000000 -> 0.023136349 | I16: =('10-Yr DCF'!C24*0.9)/180000000 -> 0.02120832
B17: 95% of Base NOI | C17: =('10-Yr DCF'!C24*0.95)/110000000 -> 0.036632553 | D17: =('10-Yr DCF'!C24*0.95)/120000000 -> 0.03357984 | E17: =('10-Yr DCF'!C24*0.95)/134600000 -> 0.02993745 | F17: =('10-Yr DCF'!C24*0.95)/145000000 -> 0.027790212 | G17: =('10-Yr DCF'!C24*0.95)/155000000 -> 0.025997295 | H17: =('10-Yr DCF'!C24*0.95)/165000000 -> 0.024421702 | I17: =('10-Yr DCF'!C24*0.95)/180000000 -> 0.02238656
B18: 100% of Base NOI | C18: =('10-Yr DCF'!C24*1)/110000000 -> 0.038560582 | D18: =('10-Yr DCF'!C24*1)/120000000 -> 0.0353472 | E18: =('10-Yr DCF'!C24*1)/134600000 -> 0.031513105 | F18: =('10-Yr DCF'!C24*1)/145000000 -> 0.029252855 | G18: =('10-Yr DCF'!C24*1)/155000000 -> 0.027365574 | H18: =('10-Yr DCF'!C24*1)/165000000 -> 0.025707055 | I18: =('10-Yr DCF'!C24*1)/180000000 -> 0.0235648
B19: 105% of Base NOI | C19: =('10-Yr DCF'!C24*1.05)/110000000 -> 0.040488611 | D19: =('10-Yr DCF'!C24*1.05)/120000000 -> 0.03711456 | E19: =('10-Yr DCF'!C24*1.05)/134600000 -> 0.033088761 | F19: =('10-Yr DCF'!C24*1.05)/145000000 -> 0.030715498 | G19: =('10-Yr DCF'!C24*1.05)/155000000 -> 0.028733853 | H19: =('10-Yr DCF'!C24*1.05)/165000000 -> 0.026992407 | I19: =('10-Yr DCF'!C24*1.05)/180000000 -> 0.02474304
B20: 110% of Base NOI | C20: =('10-Yr DCF'!C24*1.1)/110000000 -> 0.04241664 | D20: =('10-Yr DCF'!C24*1.1)/120000000 -> 0.03888192 | E20: =('10-Yr DCF'!C24*1.1)/134600000 -> 0.034664416 | F20: =('10-Yr DCF'!C24*1.1)/145000000 -> 0.032178141 | G20: =('10-Yr DCF'!C24*1.1)/155000000 -> 0.030102132 | H20: =('10-Yr DCF'!C24*1.1)/165000000 -> 0.02827776 | I20: =('10-Yr DCF'!C24*1.1)/180000000 -> 0.02592128
B23: TABLE 3: UNLEVERED IRR — RENT GROWTH (YRS 1–5) vs. EXIT CAP RATE
B24: Rent Growth \ Exit Cap → | C24: 5.50% | D24: 6.00% | E24: 6.25% | F24: 6.75% | G24: 7.25% | H24: 7.75% | I24: 8.25%
B25: 1.0% p.a. | C25: 0.0144 | D25: 0.0077 | E25: 0.0046 | F25: -0.0011 | G25: -0.0063 | H25: -0.0111 | I25: -0.0155
B26: 1.5% p.a. | C26: 0.0172 | D26: 0.0105 | E26: 0.0074 | F26: 0.0016 | G26: -0.0036 | H26: -0.0084 | I26: -0.0128
B27: 2.0% p.a. | C27: 0.0199 | D27: 0.0132 | E27: 0.0101 | F27: 0.0044 | G27: -0.0009 | H27: -0.0056 | I27: -0.01
B28: 2.5% p.a. | C28: 0.0227 | D28: 0.016 | E28: 0.0129 | F28: 0.0071 | G28: 0.0019 | H28: -0.0029 | I28: -0.0073
B29: 3.0% p.a. | C29: 0.0255 | D29: 0.0187 | E29: 0.0156 | F29: 0.0099 | G29: 0.0046 | H29: -0.0002 | I29: -0.0046
B31: Base case highlighted in green | Blue cells in Assumptions tab are editable inputs | IRR values in Table 3 are approximations for scenario illustration
