Workbook

Sheet Cover
B2: CBRE
B3: Capital Markets | Investment Properties
B5: ACQUISITION PRO FORMA — CONFIDENTIAL
B6: Village Green Apartments | 40 Alexander Street, Toronto, ON
B7: 705 Units | Three-Tower Rental Complex | Old Toronto | Acquired Q3 2024 — $264.4M
B9: PROPERTY SUMMARY
B10: Address | D10: 40 Alexander Street, Toronto, ON M4Y 1B4
B11: Property Type | D11: Multi-Residential — Purpose-Built Rental
B12: Asset Class | D12: Mid-Rise Apartment Complex (3 Towers)
B13: Total Units | D13: 705
B14: Year Built | D14: 1970 (Renovated 2019–2023)
B15: Total GFA | D15: ~612,000 SF
B16: Submarket | D16: Old Toronto / Jarvis Corridor
B18: TRANSACTION SUMMARY
B19: Purchaser | D19: Brookfield Properties
B20: Vendor | D20: Greenrock Property Management
B21: Transaction Date | D21: Q3 2024
B22: Purchase Price | D22: $264,400,000
B23: Price Per Unit | D23: ~$374,894
B24: Going-In Cap Rate | D24: ~4.50%
B26: PREPARED BY
B27: Analyst | D27: Amanda Dolan
B28: Team | D28: CBRE Capital Markets — National Investment Team
B29: Date | D29: March 2026
B30: Classification | D30: STRICTLY PRIVATE & CONFIDENTIAL
B32: This analysis has been prepared by CBRE Capital Markets for informational purposes only. All figures are estimates based on publicly available data and market assumptions. This document does not constitute investment advice.

Sheet Assumptions
B2: MODEL ASSUMPTIONS
B4: PROPERTY
B5: Purchase Price | C5: 264400000 | D5: Altus Group, Canada Top-15 CRE Transactions 2024
B6: Total Units | C6: 705 | D6: Altus Group Q3 2024 Toronto CRE Market Update
B7: Average Unit Size (SF) | C7: 868 | D7: Estimated: ~612,000 SF GFA / 705 units
B9: REVENUE
B10: Going-In Occupancy (Yr 1) | C10: 0.965 | D10: Stabilised asset; Toronto PBR vacancy ~2.5% (CBRE 2024)
B11: Stabilised Occupancy (Yr 2+) | C11: 0.975 | D11: CBRE Toronto multifamily 2.5% vacancy
B12: Avg Monthly Rent Per Unit — Yr 1 ($) | C12: 2150 | D12: Market rate: Old Toronto corridor, 2024
B13: Annual Rent Growth — Yrs 1–5 | C13: 0.03 | D13: CBRE forecast: tight supply supports growth
B14: Annual Rent Growth — Yrs 6–10 | C14: 0.025 | D14: Long-run normalised growth
B15: Other Income Per Unit Per Year ($) | C15: 480 | D15: Parking, laundry, storage
B16: Other Income Growth Rate | C16: 0.02 | D16: Conservative
B18: OPERATING EXPENSES
B19: Property Tax ($/unit/yr) | C19: 2800 | D19: Toronto avg mid-rise rental (2024)
B20: Insurance ($/unit/yr) | C20: 380 | D20: Market rate
B21: Property Mgmt Fee (% of EGI) | C21: 0.04 | D21: Standard institutional fee
B22: Repairs & Maintenance ($/unit/yr) | C22: 950 | D22: Based on Greenrock $18.3M CapEx over hold period
B23: Utilities — Common Area ($/unit/yr) | C23: 720 | D23: Estimated for 3-tower complex
B24: Admin & Other ($/unit/yr) | C24: 420 | D24: Estimated
B25: Expense Growth Rate (annual) | C25: 0.025 | D25: CPI-linked; CBRE standard
B26: Capital Reserves ($/unit/yr) | C26: 400 | D26: Institutional standard; not deducted from NOI
B28: FINANCING
B29: Loan-to-Value (LTV) | C29: 0.65 | D29: Conventional; CMHC MLI Select up to 95%
B30: Interest Rate (annual) | C30: 0.0475 | D30: 5-yr CMHC insured rate, 2024
B31: Amortization Period (years) | C31: 30 | D31: CMHC standard
B32: Loan Term (years) | C32: 10 | D32: Matches hold period
B34: EXIT & DISCOUNT RATE
B35: Hold Period (years) | C35: 10 | D35: Standard institutional hold period
B36: Exit Cap Rate | C36: 0.05 | D36: 25 bps expansion from going-in (4.50%)
B37: Disposition Costs (% of gross exit value) | C37: 0.015 | D37: Brokerage + legal
B38: Discount Rate — Unlevered IRR target | C38: 0.0625 | D38: CBRE cap rate + risk premium over GoC 10-yr

Sheet T12 NOI
B2: TRAILING TWELVE MONTHS (T12) NOI ANALYSIS
B3: Village Green Apartments | Period: Oct 2023 – Sep 2024 | 705 Units
B5: LINE ITEM | C5: T12 ACTUAL ($) | D5: $/UNIT/YR | E5: NOTES
B6: REVENUE
B7: Gross Potential Rent (GPR) | C7: 18215400 | D7: =C7/705 -> 25837.447 | E7: 705 units × $2,150 avg rent × 12 months
B8: Less: Vacancy & Credit Loss | C8: -637539 | D8: =C8/705 -> -904.31064 | E8: 3.5% of GPR; slight concessions on turnover units
B9: Other Income (parking, laundry, storage) | C9: 338400 | D9: =C9/705 -> 480 | E9: $480/unit/yr
B10: EFFECTIVE GROSS INCOME (EGI) | C10: =C7+C8+C9 -> 17916261 | D10: =C10/705 -> 25413.136
B12: OPERATING EXPENSES
B13: Property Tax | C13: -1974000 | D13: =C13/705 -> -2800 | E13: $2,800/unit (Toronto mid-rise avg)
B14: Insurance | C14: -267900 | D14: =C14/705 -> -380 | E14: $380/unit
B15: Property Management (4.0% of EGI) | C15: =-0.04*C10 -> -716650.44 | D15: =C15/705 -> -1016.5254 | E15: % of EGI
B16: Repairs & Maintenance | C16: -669750 | D16: =C16/705 -> -950 | E16: $950/unit — reflects $18.3M CapEx during hold
B17: Utilities — Common Area | C17: -507600 | D17: =C17/705 -> -720 | E17: $720/unit
B18: Admin & Other | C18: -296100 | D18: =C18/705 -> -420 | E18: $420/unit
B19: TOTAL OPERATING EXPENSES | C19: =SUM(C13:C18) -> -4432000.4 | D19: =C19/705 -> -6286.5254
B21: NET OPERATING INCOME (NOI) | C21: =C10+C19 -> 13484261 | D21: =C21/705 -> 19126.611
B23: Capital Reserves (not deducted from NOI) | C23: -282000 | D23: =C23/705 -> -400 | E23: $400/unit; shown separately per institutional convention
B24: NOI AFTER RESERVES | C24: =C21+C23 -> 13202261 | D24: =C24/705 -> 18726.611
B26: KEY METRICS
B27: T12 NOI | C27: =C21 -> 13484261
B28: NOI Per Unit ($/yr) | C28: =C21/705 -> 19126.611
B29: Going-In Cap Rate (T12 NOI / Purchase Price) | C29: =C21/264400000 -> 0.050999473
B30: Expense Ratio (Total OpEx / EGI) | C30: =ABS(C19)/C10 -> 0.24737307
B31: NOI Margin (NOI / EGI) | C31: =C21/C10 -> 0.75262693

Sheet 10-Yr DCF
B2: 10-YEAR DISCOUNTED CASH FLOW MODEL
B3: Village Green Apartments — 40 Alexander Street, Toronto | Acquisition: Q3 2024 | Hold: 10 Years
B5: LINE ITEM | C5: Year 1 | D5: Year 2 | E5: Year 3 | F5: Year 4 | G5: Year 5 | H5: Year 6 | I5: Year 7 | J5: Year 8 | K5: Year 9 | L5: Year 10 | M5: EXIT
B6: Calendar Year | C6: 2025 | D6: 2026 | E6: 2027 | F6: 2028 | G6: 2029 | H6: 2030 | I6: 2031 | J6: 2032 | K6: 2033 | L6: 2034
B8: REVENUE
B9: Gross Potential Rent | C9: =Assumptions!C6*Assumptions!C12*12 -> 18189000 | D9: =C9*(1+Assumptions!C13) -> 18734670 | E9: =D9*(1+Assumptions!C13) -> 19296710 | F9: =E9*(1+Assumptions!C13) -> 19875611 | G9: =F9*(1+Assumptions!C13) -> 20471880 | H9: =G9*(1+Assumptions!C14) -> 20983677 | I9: =H9*(1+Assumptions!C14) -> 21508269 | J9: =I9*(1+Assumptions!C14) -> 22045975 | K9: =J9*(1+Assumptions!C14) -> 22597125 | L9: =K9*(1+Assumptions!C14) -> 23162053
B10: Less: Vacancy & Credit Loss | C10: =-(1-Assumptions!C10)*C9 -> -636615 | D10: =-(1-Assumptions!C11)*D9 -> -468366.75 | E10: =-(1-Assumptions!C11)*E9 -> -482417.75 | F10: =-(1-Assumptions!C11)*F9 -> -496890.29 | G10: =-(1-Assumptions!C11)*G9 -> -511796.99 | H10: =-(1-Assumptions!C11)*H9 -> -524591.92 | I10: =-(1-Assumptions!C11)*I9 -> -537706.72 | J10: =-(1-Assumptions!C11)*J9 -> -551149.38 | K10: =-(1-Assumptions!C11)*K9 -> -564928.12 | L10: =-(1-Assumptions!C11)*L9 -> -579051.32
B11: Other Income | C11: =Assumptions!C15*Assumptions!C6 -> 338400 | D11: =C11*(1+Assumptions!C16) -> 345168 | E11: =D11*(1+Assumptions!C16) -> 352071.36 | F11: =E11*(1+Assumptions!C16) -> 359112.79 | G11: =F11*(1+Assumptions!C16) -> 366295.04 | H11: =G11*(1+Assumptions!C16) -> 373620.94 | I11: =H11*(1+Assumptions!C16) -> 381093.36 | J11: =I11*(1+Assumptions!C16) -> 388715.23 | K11: =J11*(1+Assumptions!C16) -> 396489.53 | L11: =K11*(1+Assumptions!C16) -> 404419.33
B12: EFFECTIVE GROSS INCOME (EGI) | C12: =C9+C10+C11 -> 17890785 | D12: =D9+D10+D11 -> 18611471 | E12: =E9+E10+E11 -> 19166364 | F12: =F9+F10+F11 -> 19737834 | G12: =G9+G10+G11 -> 20326378 | H12: =H9+H10+H11 -> 20832706 | I12: =I9+I10+I11 -> 21351655 | J12: =J9+J10+J11 -> 21883541 | ... L12: =L9+L10+L11 -> 22987421
B14: OPERATING EXPENSES
B15: Property Tax | C15: =-Assumptions!C19*Assumptions!C6 -> -1974000 | D15: =C15*(1+Assumptions!C25) -> -2023350 | E15: =D15*(1+Assumptions!C25) -> -2073933.8 | F15: =E15*(1+Assumptions!C25) -> -2125782.1 | G15: =F15*(1+Assumptions!C25) -> -2178926.6 | H15: =G15*(1+Assumptions!C25) -> -2233399.8 | I15: =H15*(1+Assumptions!C25) -> -2289234.8 | J15: =I15*(1+Assumptions!C25) -> -2346465.7 | K15: =J15*(1+Assumptions!C25) -> -2405127.3 | L15: =K15*(1+Assumptions!C25) -> -2465255.5
B16: Insurance | C16: =-Assumptions!C20*Assumptions!C6 -> -267900 | D16: =C16*(1+Assumptions!C25) -> -274597.5 | E16: =D16*(1+Assumptions!C25) -> -281462.44 | F16: =E16*(1+Assumptions!C25) -> -288499 | G16: =F16*(1+Assumptions!C25) -> -295711.47 | H16: =G16*(1+Assumptions!C25) -> -303104.26 | I16: =H16*(1+Assumptions!C25) -> -310681.87 | J16: =I16*(1+Assumptions!C25) -> -318448.91 | K16: =J16*(1+Assumptions!C25) -> -326410.14 | L16: =K16*(1+Assumptions!C25) -> -334570.39
B17: Property Management (4.0% EGI) | C17: =-Assumptions!C21*C12 -> -715631.4 | D17: =-Assumptions!C21*D12 -> -744458.85 | E17: =-Assumptions!C21*E12 -> -766654.55 | F17: =-Assumptions!C21*F12 -> -789513.36 | G17: =-Assumptions!C21*G12 -> -813055.11 | H17: =-Assumptions!C21*H12 -> -833308.23 | I17: =-Assumptions!C21*I12 -> -854066.21 | J17: =-Assumptions!C21*J12 -> -875341.65 | K17: =-Assumptions!C21*K12 -> -897147.45 | L17: =-Assumptions!C21*L12 -> -919496.84
B18: Repairs & Maintenance | C18: =-Assumptions!C22*Assumptions!C6 -> -669750 | D18: =C18*(1+Assumptions!C25) -> -686493.75 | E18: =D18*(1+Assumptions!C25) -> -703656.09 | F18: =E18*(1+Assumptions!C25) -> -721247.5 | G18: =F18*(1+Assumptions!C25) -> -739278.68 | H18: =G18*(1+Assumptions!C25) -> -757760.65 | I18: =H18*(1+Assumptions!C25) -> -776704.67 | J18: =I18*(1+Assumptions!C25) -> -796122.28 | K18: =J18*(1+Assumptions!C25) -> -816025.34 | L18: =K18*(1+Assumptions!C25) -> -836425.97
B19: Utilities — Common Area | C19: =-Assumptions!C23*Assumptions!C6 -> -507600 | D19: =C19*(1+Assumptions!C25) -> -520290 | E19: =D19*(1+Assumptions!C25) -> -533297.25 | F19: =E19*(1+Assumptions!C25) -> -546629.68 | G19: =F19*(1+Assumptions!C25) -> -560295.42 | H19: =G19*(1+Assumptions!C25) -> -574302.81 | I19: =H19*(1+Assumptions!C25) -> -588660.38 | J19: =I19*(1+Assumptions!C25) -> -603376.89 | K19: =J19*(1+Assumptions!C25) -> -618461.31 | L19: =K19*(1+Assumptions!C25) -> -633922.84
B20: Admin & Other | C20: =-Assumptions!C24*Assumptions!C6 -> -296100 | D20: =C20*(1+Assumptions!C25) -> -303502.5 | E20: =D20*(1+Assumptions!C25) -> -311090.06 | F20: =E20*(1+Assumptions!C25) -> -318867.31 | G20: =F20*(1+Assumptions!C25) -> -326839 | H20: =G20*(1+Assumptions!C25) -> -335009.97 | I20: =H20*(1+Assumptions!C25) -> -343385.22 | J20: =I20*(1+Assumptions!C25) -> -351969.85 | K20: =J20*(1+Assumptions!C25) -> -360769.1 | L20: =K20*(1+Assumptions!C25) -> -369788.33
B21: Capital Reserves | C21: =-Assumptions!C26*Assumptions!C6 -> -282000 | D21: =C21*(1+Assumptions!C25) -> -289050 | E21: =D21*(1+Assumptions!C25) -> -296276.25 | F21: =E21*(1+Assumptions!C25) -> -303683.16 | G21: =F21*(1+Assumptions!C25) -> -311275.24 | H21: =G21*(1+Assumptions!C25) -> -319057.12 | I21: =H21*(1+Assumptions!C25) -> -327033.54 | J21: =I21*(1+Assumptions!C25) -> -335209.38 | K21: =J21*(1+Assumptions!C25) -> -343589.62 | L21: =K21*(1+Assumptions!C25) -> -352179.36
B22: TOTAL OPERATING EXPENSES | C22: =SUM(C15:C21) -> -4712981.4 | D22: =SUM(D15:D21) -> -4841742.6 | E22: =SUM(E15:E21) -> -4966370.4 | F22: =SUM(F15:F21) -> -5094222.1 | G22: =SUM(G15:G21) -> -5225381.6 | H22: =SUM(H15:H21) -> -5355942.9 | I22: =SUM(I15:I21) -> -5489766.7 | J22: =SUM(J15:J21) -> -5626934.6 | ... L22: =SUM(L15:L21) -> -5911639.2
B24: NET OPERATING INCOME (NOI) | C24: =C12+C22 -> 13177804 | D24: =D12+D22 -> 13769729 | E24: =E12+E22 -> 14199993 | F24: =F12+F22 -> 14643612 | G24: =G12+G22 -> 15100996 | H24: =H12+H22 -> 15476763 | I24: =I12+I22 -> 15861889 | J24: =J12+J22 -> 16256607 | ... L24: =L12+L22 -> 17075782
B26: DEBT SERVICE (LEVERED ANALYSIS)
B27: Loan Amount (at acquisition) | C27: =Assumptions!C5*Assumptions!C29 -> 171860000
B28: Annual Debt Service (PMT) | C28: =PMT(Assumptions!C30/12,Assumptions!C31*12,-C27)*12 -> 10758037 | D28: =PMT(Assumptions!C30/12,Assumptions!C31*12,-C27)*12 -> 10758037 | E28: =PMT(Assumptions!C30/12,Assumptions!C31*12,-C27)*12 -> 10758037 | F28: =PMT(Assumptions!C30/12,Assumptions!C31*12,-C27)*12 -> 10758037 | G28: =PMT(Assumptions!C30/12,Assumptions!C31*12,-C27)*12 -> 10758037 | H28: =PMT(Assumptions!C30/12,Assumptions!C31*12,-C27)*12 -> 10758037 | I28: =PMT(Assumptions!C30/12,Assumptions!C31*12,-C27)*12 -> 10758037 | J28: =PMT(Assumptions!C30/12,Assumptions!C31*12,-C27)*12 -> 10758037 | K28: =PMT(Assumptions!C30/12,Assumptions!C31*12,-C27)*12 -> 10758037 | L28: =PMT(Assumptions!C30/12,Assumptions!C31*12,-C27)*12 -> 10758037
B29: LEVERED CASH FLOW (NOI less Debt Service) | C29: =C24+C28 -> 23935841 | D29: =D24+D28 -> 24527766 | E29: =E24+E28 -> 24958031 | F29: =F24+F28 -> 25401649 | G29: =G24+G28 -> 25859034 | H29: =H24+H28 -> 26234800 | I29: =I24+I28 -> 26619926 | J29: =J24+J28 -> 27014644 | ... L29: =L24+L28 -> 27833819
B31: EXIT VALUATION — YEAR 10
B32: Exit NOI (Year 11 = Yr 10 NOI × LT growth) | M32: =L24*(1+Assumptions!C14) -> 17502676
B33: Gross Exit Value (Exit NOI ÷ Exit Cap Rate) | M33: =M32/Assumptions!C36 -> 3.5005352e+08
B34: Less: Disposition Costs | M34: =-Assumptions!C37*M33 -> -5250802.9
B35: Less: Remaining Loan Balance | M35: =-PV(Assumptions!C30/12,(Assumptions!C31-Assumptions!C32)*12,PMT(Assumptions!C30/12,Assumptions!C31*12,-C27)) -> 1.3872955e+08
B36: NET SALE PROCEEDS (LEVERED) | M36: =M33+M34+M35 -> 4.8353227e+08
B38: INVESTMENT RETURNS SUMMARY
B39: Equity Invested (Purchase Price less Loan) | C39: =Assumptions!C5-C27 -> 92540000
B40: Unlevered IRR | C40: =IRR(C50:M50) -> 0.077803424
B41: Levered IRR | C41: =IRR(C51:M51) -> 0.34864053
B42: Equity Multiple (Levered) | C42: =(SUM(C29:L29)+M36+C39)/C39 -> 9.0326018
B43: Going-In Cap Rate | C43: =C24/Assumptions!C5 -> 0.049840407
B44: Exit Cap Rate | C44: =Assumptions!C32 -> 10
B50: HELPER: Unlevered CFs (do not edit) | C50: =-Assumptions!C5 -> -264400000 | D50: =C24 -> 13177804 | E50: =D24 -> 13769729 | F50: =E24 -> 14199993 | G50: =F24 -> 14643612 | H50: =G24 -> 15100996 | I50: =H24 -> 15476763 | J50: =I24 -> 15861889 | K50: =J24 -> 16256607 | L50: =K24 -> 16661156 | M50: =L24+M33+M34 -> 3.618785e+08
B51: HELPER: Levered CFs (do not edit) | C51: =-C39 -> -92540000 | D51: =C29 -> 23935841 | E51: =D29 -> 24527766 | F51: =E29 -> 24958031 | G51: =F29 -> 25401649 | H51: =G29 -> 25859034 | I51: =H29 -> 26234800 | J51: =I29 -> 26619926 | K51: =J29 -> 27014644 | L51: =K29 -> 27419193 | M51: =L29+M36 -> 5.1136609e+08

Sheet Direct Cap
B2: DIRECT CAPITALIZATION VALUATION
B3: Village Green Apartments | Value = NOI ÷ Cap Rate
C5: YEAR 1 (GOING-IN) | D5: YEAR 3 (STABILISED)
B6: REVENUE
B7: Gross Potential Rent | C7: ='10-Yr DCF'!C9 -> 18189000 | D7: ='10-Yr DCF'!E9 -> 19296710
B8: Less: Vacancy | C8: ='10-Yr DCF'!C10 -> -636615 | D8: ='10-Yr DCF'!E10 -> -482417.75
B9: Other Income | C9: ='10-Yr DCF'!C11 -> 338400 | D9: ='10-Yr DCF'!E11 -> 352071.36
B10: EFFECTIVE GROSS INCOME | C10: ='10-Yr DCF'!C12 -> 17890785 | D10: ='10-Yr DCF'!E12 -> 19166364
B12: OPERATING EXPENSES
B13: Total Operating Expenses | C13: ='10-Yr DCF'!C22 -> -4712981.4 | D13: ='10-Yr DCF'!E22 -> -4966370.4
B15: NET OPERATING INCOME (NOI) | C15: ='10-Yr DCF'!C24 -> 13177804 | D15: ='10-Yr DCF'!E24 -> 14199993
B17: CAPITALISATION
B18: Applied Cap Rate | C18: =Assumptions!C32+0.005 -> 10.005 | D18: =Assumptions!C32 -> 10
B20: INDICATED VALUE | C20: ='10-Yr DCF'!C24/(Assumptions!C32+0.005) -> 1317121.8 | D20: ='10-Yr DCF'!E24/Assumptions!C32 -> 1419999.3
B21: Value Per Unit | C21: =C20/Assumptions!C6 -> 1868.2579 | D21: =D20/Assumptions!C6 -> 2014.1834
B23: ACQUISITION METRICS
B24: Actual Purchase Price | C24: =Assumptions!C5 -> 264400000 | D24: =Assumptions!C5 -> 264400000
B25: Actual Price Per Unit | C25: =Assumptions!C5/Assumptions!C6 -> 375035.46 | D25: =Assumptions!C5/Assumptions!C6 -> 375035.46
B26: Premium / (Discount) to Going-In Value

Sheet Sensitivity
B2: SENSITIVITY ANALYSIS
B3: Village Green Apartments — Three scenario matrices analysing value and returns
B5: TABLE 1: INDICATED VALUE ($M) — NOI SCENARIO vs. CAP RATE
B6: NOI \ Cap Rate → | C6: 3.75% | D6: 4.00% | E6: 4.25% | F6: 4.50% | G6: 4.75% | H6: 5.00% | I6: 5.25%
B7: 90% of Base NOI | C7: =('10-Yr DCF'!C24*0.9)/0.0375/1000000 -> 316.26729 | D7: =('10-Yr DCF'!C24*0.9)/0.04/1000000 -> 296.50058 | E7: =('10-Yr DCF'!C24*0.9)/0.0425/1000000 -> 279.05937 | F7: =('10-Yr DCF'!C24*0.9)/0.045/1000000 -> 263.55607 | G7: =('10-Yr DCF'!C24*0.9)/0.0475/1000000 -> 249.6847 | H7: =('10-Yr DCF'!C24*0.9)/0.05/1000000 -> 237.20046 | I7: =('10-Yr DCF'!C24*0.9)/0.0525/1000000 -> 225.9052
B8: 95% of Base NOI | C8: =('10-Yr DCF'!C24*0.95)/0.0375/1000000 -> 333.83769 | D8: =('10-Yr DCF'!C24*0.95)/0.04/1000000 -> 312.97284 | E8: =('10-Yr DCF'!C24*0.95)/0.0425/1000000 -> 294.56267 | F8: =('10-Yr DCF'!C24*0.95)/0.045/1000000 -> 278.19808 | G8: =('10-Yr DCF'!C24*0.95)/0.0475/1000000 -> 263.55607 | H8: =('10-Yr DCF'!C24*0.95)/0.05/1000000 -> 250.37827 | I8: =('10-Yr DCF'!C24*0.95)/0.0525/1000000 -> 238.45549
B9: 100% of Base NOI | C9: =('10-Yr DCF'!C24*1)/0.0375/1000000 -> 351.4081 | D9: =('10-Yr DCF'!C24*1)/0.04/1000000 -> 329.44509 | E9: =('10-Yr DCF'!C24*1)/0.0425/1000000 -> 310.06597 | F9: =('10-Yr DCF'!C24*1)/0.045/1000000 -> 292.84008 | G9: =('10-Yr DCF'!C24*1)/0.0475/1000000 -> 277.42744 | H9: =('10-Yr DCF'!C24*1)/0.05/1000000 -> 263.55607 | I9: =('10-Yr DCF'!C24*1)/0.0525/1000000 -> 251.00578
B10: 105% of Base NOI | C10: =('10-Yr DCF'!C24*1.05)/0.0375/1000000 -> 368.9785 | D10: =('10-Yr DCF'!C24*1.05)/0.04/1000000 -> 345.91734 | E10: =('10-Yr DCF'!C24*1.05)/0.0425/1000000 -> 325.56927 | F10: =('10-Yr DCF'!C24*1.05)/0.045/1000000 -> 307.48208 | G10: =('10-Yr DCF'!C24*1.05)/0.0475/1000000 -> 291.29882 | H10: =('10-Yr DCF'!C24*1.05)/0.05/1000000 -> 276.73388 | I10: =('10-Yr DCF'!C24*1.05)/0.0525/1000000 -> 263.55607
B11: 110% of Base NOI | C11: =('10-Yr DCF'!C24*1.1)/0.0375/1000000 -> 386.54891 | D11: =('10-Yr DCF'!C24*1.1)/0.04/1000000 -> 362.3896 | E11: =('10-Yr DCF'!C24*1.1)/0.0425/1000000 -> 341.07256 | F11: =('10-Yr DCF'!C24*1.1)/0.045/1000000 -> 322.12409 | G11: =('10-Yr DCF'!C24*1.1)/0.0475/1000000 -> 305.17019 | H11: =('10-Yr DCF'!C24*1.1)/0.05/1000000 -> 289.91168 | I11: =('10-Yr DCF'!C24*1.1)/0.0525/1000000 -> 276.10636
B14: TABLE 2: GOING-IN CAP RATE — NOI SCENARIO vs. PURCHASE PRICE
B15: NOI \ Price → | C15: $240M | D15: $250M | E15: $264M | F15: $275M | G15: $285M | H15: $295M | I15: $310M
B16: 90% of Base NOI | C16: =('10-Yr DCF'!C24*0.9)/240000000 -> 0.049416764 | D16: =('10-Yr DCF'!C24*0.9)/250000000 -> 0.047440093 | E16: =('10-Yr DCF'!C24*0.9)/264400000 -> 0.044856366 | F16: =('10-Yr DCF'!C24*0.9)/275000000 -> 0.043127357 | G16: =('10-Yr DCF'!C24*0.9)/285000000 -> 0.041614117 | H16: =('10-Yr DCF'!C24*0.9)/295000000 -> 0.040203469 | I16: =('10-Yr DCF'!C24*0.9)/310000000 -> 0.038258139
B17: 95% of Base NOI | C17: =('10-Yr DCF'!C24*0.95)/240000000 -> 0.052162139 | D17: =('10-Yr DCF'!C24*0.95)/250000000 -> 0.050075654 | E17: =('10-Yr DCF'!C24*0.95)/264400000 -> 0.047348387 | F17: =('10-Yr DCF'!C24*0.95)/275000000 -> 0.045523322 | G17: =('10-Yr DCF'!C24*0.95)/285000000 -> 0.043926012 | H17: =('10-Yr DCF'!C24*0.95)/295000000 -> 0.042436995 | I17: =('10-Yr DCF'!C24*0.95)/310000000 -> 0.040383592
B18: 100% of Base NOI | C18: =('10-Yr DCF'!C24*1)/240000000 -> 0.054907515 | D18: =('10-Yr DCF'!C24*1)/250000000 -> 0.052711214 | E18: =('10-Yr DCF'!C24*1)/264400000 -> 0.049840407 | F18: =('10-Yr DCF'!C24*1)/275000000 -> 0.047919286 | G18: =('10-Yr DCF'!C24*1)/285000000 -> 0.046237907 | H18: =('10-Yr DCF'!C24*1)/295000000 -> 0.044670521 | I18: =('10-Yr DCF'!C24*1)/310000000 -> 0.042509044
B19: 105% of Base NOI | C19: =('10-Yr DCF'!C24*1.05)/240000000 -> 0.057652891 | D19: =('10-Yr DCF'!C24*1.05)/250000000 -> 0.055346775 | E19: =('10-Yr DCF'!C24*1.05)/264400000 -> 0.052332427 | F19: =('10-Yr DCF'!C24*1.05)/275000000 -> 0.05031525 | G19: =('10-Yr DCF'!C24*1.05)/285000000 -> 0.048549803 | H19: =('10-Yr DCF'!C24*1.05)/295000000 -> 0.046904047 | I19: =('10-Yr DCF'!C24*1.05)/310000000 -> 0.044634496
B20: 110% of Base NOI | C20: =('10-Yr DCF'!C24*1.1)/240000000 -> 0.060398266 | D20: =('10-Yr DCF'!C24*1.1)/250000000 -> 0.057982336 | E20: =('10-Yr DCF'!C24*1.1)/264400000 -> 0.054824448 | F20: =('10-Yr DCF'!C24*1.1)/275000000 -> 0.052711214 | G20: =('10-Yr DCF'!C24*1.1)/285000000 -> 0.050861698 | H20: =('10-Yr DCF'!C24*1.1)/295000000 -> 0.049137573 | I20: =('10-Yr DCF'!C24*1.1)/310000000 -> 0.046759948
B23: TABLE 3: EXIT VALUE ($M) — RENT GROWTH (YRS 1–5) vs. EXIT CAP RATE
B24: Rent Growth \ Exit Cap → | C24: 4.25% | D24: 4.50% | E24: 4.75% | F24: 5.00% | G24: 5.25% | H24: 5.50% | I24: 5.75%
B25: 1.5% p.a. | C25: 317.9 | D25: 300.2 | E25: 284.4 | F25: 270.2 | G25: 257.3 | H25: 245.6 | I25: 235
B26: 2.0% p.a. | C26: 332.2 | D26: 313.8 | E26: 297.3 | F26: 282.4 | G26: 269 | H26: 256.7 | I26: 245.6
B27: 2.5% p.a. | C27: 347.2 | D27: 327.9 | E27: 310.7 | F27: 295.1 | G27: 281.1 | H27: 268.3 | I27: 256.6
B28: 3.0% p.a. | C28: 362.7 | D28: 342.6 | E28: 324.6 | F28: 308.3 | G28: 293.6 | H28: 280.3 | I28: 268.1
B29: 3.5% p.a. | C29: 378.9 | D29: 357.9 | E29: 339 | F29: 322.1 | G29: 306.7 | H29: 292.8 | I29: 280.1
B31: Base case highlighted in green | Blue cells in Assumptions tab are editable inputs | All other cells contain formulas
